xtcryptosignals/__init__.py
xtcryptosignals/app_client.py
xtcryptosignals/app_server.py
xtcryptosignals/app_tasks.py
xtcryptosignals/settings.py
xtcryptosignals/settings_exchanges.py
xtcryptosignals/client/__init__.py
xtcryptosignals/client/config.py
xtcryptosignals/client/service.py
xtcryptosignals/client/utils.py
xtcryptosignals/client/api/__init__.py
xtcryptosignals/client/api/auth/__init__.py
xtcryptosignals/client/api/auth/models.py
xtcryptosignals/client/api/auth/views.py
xtcryptosignals/client/api/charts/__init__.py
xtcryptosignals/client/api/charts/views.py
xtcryptosignals/client/api/contact/__init__.py
xtcryptosignals/client/api/contact/views.py
xtcryptosignals/client/api/errors/__init__.py
xtcryptosignals/client/api/errors/views.py
xtcryptosignals/client/api/exchanges/__init__.py
xtcryptosignals/client/api/exchanges/views.py
xtcryptosignals/client/api/home/__init__.py
xtcryptosignals/client/api/home/views.py
xtcryptosignals/client/api/notifications/__init__.py
xtcryptosignals/client/api/notifications/views.py
xtcryptosignals/client/api/parties/__init__.py
xtcryptosignals/client/api/parties/views.py
xtcryptosignals/client/api/portfolio/__init__.py
xtcryptosignals/client/api/portfolio/views.py
xtcryptosignals/client/api/tickers/__init__.py
xtcryptosignals/client/api/tickers/views.py
xtcryptosignals/client/api/tools/__init__.py
xtcryptosignals/client/api/tools/views.py
xtcryptosignals/client/api/transactions/__init__.py
xtcryptosignals/client/api/transactions/views.py
xtcryptosignals/client/api/user/__init__.py
xtcryptosignals/client/api/user/views.py
xtcryptosignals/client/static/css/custom.css
xtcryptosignals/client/static/css/darkmode.css
xtcryptosignals/client/static/css/fonts/fontawesome-webfont.ttf
xtcryptosignals/client/static/css/fonts/fontawesome-webfont.woff
xtcryptosignals/client/static/css/fonts/fontawesome-webfont.woff2
xtcryptosignals/client/static/css/landing/custom.css
xtcryptosignals/client/static/css/notify/styles/notify-metro.css
XTCryptoSignals-1.0.3.dist-info/LICENSE
XTCryptoSignals-1.0.3.dist-info/METADATA
XTCryptoSignals-1.0.3.dist-info/WHEEL
XTCryptoSignals-1.0.3.dist-info/entry_points.txt
XTCryptoSignals-1.0.3.dist-info/top_level.txt
XTCryptoSignals-1.0.3.dist-info/RECORD
