Metadata-Version: 2.1
Name: XTCryptoSignals
Version: 1.0.3
Summary: Platform that collects cryptocurrencies price data, fires alerts based on price sentiment and many other features.
Home-page: https://xtcryptosignals.com
Author: Paulo Antunes
Author-email: pjmlantunes@gmail.com
Maintainer: Paulo Antunes
Maintainer-email: pjmlantunes@gmail.com
License: GPL
Keywords: xtcryptosignals,api,cryptocurrency,bitcoin,ethereum,signals,trading,crypto signals,exchange,crypto
Classifier: Development Status :: 5 - Production/Stable
Classifier: Intended Audience :: Developers
Classifier: Intended Audience :: Financial and Insurance Industry
Classifier: Topic :: Software Development :: Libraries :: Python Modules
Classifier: License :: OSI Approved :: GNU General Public License v3 (GPLv3)
Classifier: Operating System :: OS Independent
Classifier: Natural Language :: English
Classifier: Programming Language :: Python :: 3.7
Requires-Python: >=3.7
License-File: LICENSE
Requires-Dist: amqp==2.6.1
Requires-Dist: aniso8601==9.0.1
Requires-Dist: apscheduler==3.6.3
Requires-Dist: attrs==21.2.0
Requires-Dist: autobahn==21.3.1
Requires-Dist: automat==20.2.0
Requires-Dist: bcrypt==3.2.0
Requires-Dist: beautifulsoup4==4.9.3
Requires-Dist: bidict==0.21.2
Requires-Dist: billiard==3.6.4.0
Requires-Dist: cachelib==0.2.0
Requires-Dist: cachetools==4.2.2
Requires-Dist: captcha==0.3
Requires-Dist: celery==4.4.6
Requires-Dist: certifi==2021.5.30
Requires-Dist: cffi==1.14.5
Requires-Dist: cfscrape==2.1.1
Requires-Dist: chardet==3.0.4
Requires-Dist: click==8.0.1
Requires-Dist: configparser==5.0.2
Requires-Dist: constantly==15.1.0
Requires-Dist: cryptography==3.4.7
Requires-Dist: dateparser==1.0.0
Requires-Dist: dnspython==1.16.0
Requires-Dist: environs==9.3.2
Requires-Dist: eventlet==0.26.0
Requires-Dist: flasgger==0.9.5
Requires-Dist: flask==2.0.1
Requires-Dist: flask-login==0.5.0
Requires-Dist: flask-restful==0.3.9
Requires-Dist: flask-session==0.3.2
Requires-Dist: flask-socketio==5.1.0
Requires-Dist: flask-wtf==0.15.1
Requires-Dist: future==0.18.2
Requires-Dist: greenlet==1.1.0
Requires-Dist: gunicorn==20.1.0
Requires-Dist: http-ece==1.1.0
Requires-Dist: hyperlink==21.0.0
Requires-Dist: idna==2.10
Requires-Dist: importlib-metadata==4.6.0
Requires-Dist: incremental==21.3.0
Requires-Dist: itsdangerous==2.0.1
Requires-Dist: jinja2==3.0.1
Requires-Dist: jsonschema==3.2.0
Requires-Dist: kombu==4.6.11
Requires-Dist: markupsafe==2.0.1
Requires-Dist: marshmallow==2.20.5
Requires-Dist: millify==0.1.1
Requires-Dist: mistune==0.8.4
Requires-Dist: mongodb-migrations==1.0.1
Requires-Dist: mongoengine==0.23.1
Requires-Dist: monotonic==1.6
Requires-Dist: pep517==0.10.0
Requires-Dist: pillow==8.3.0
Requires-Dist: pip-tools==6.2.0
Requires-Dist: py-etherscan-api==0.8.0
Requires-Dist: py-vapid==1.8.2
Requires-Dist: pyasn1==0.4.8
Requires-Dist: pyasn1-modules==0.2.8
Requires-Dist: pycparser==2.20
Requires-Dist: pycryptodome==3.10.1
Requires-Dist: pymongo==3.10.1
Requires-Dist: pyopenssl==20.0.1
Requires-Dist: pyrsistent==0.18.0
Requires-Dist: python-binance==0.7.9
Requires-Dist: python-dateutil==2.8.1
Requires-Dist: python-dotenv==0.18.0
Requires-Dist: python-engineio==4.2.0
Requires-Dist: python-kucoin==2.1.2
Requires-Dist: python-socketio[client]==5.3.0
Requires-Dist: python-telegram-bot==13.6
Requires-Dist: pytz==2021.1
Requires-Dist: pywebpush==1.13.0
Requires-Dist: pyyaml==5.4.1
Requires-Dist: redis==3.5.3
Requires-Dist: regex==2021.7.1
Requires-Dist: requests==2.23.0
Requires-Dist: service-identity==21.1.0
Requires-Dist: six==1.16.0
Requires-Dist: soupsieve==2.2.1
Requires-Dist: toml==0.10.2
Requires-Dist: tornado==6.1
Requires-Dist: twisted==21.2.0
Requires-Dist: txaio==21.2.1
Requires-Dist: typing-extensions==3.10.0.0
Requires-Dist: tzlocal==2.1
Requires-Dist: ujson==4.0.2
Requires-Dist: urllib3==1.25.11
Requires-Dist: vine==1.3.0
Requires-Dist: websocket-client==1.1.0
Requires-Dist: websockets==9.1
Requires-Dist: werkzeug==2.0.1
Requires-Dist: wheel==0.36.2
Requires-Dist: wikipedia-api==0.5.4
Requires-Dist: wtforms==2.3.3
Requires-Dist: zipp==3.5.0
Requires-Dist: zope.interface==5.4.0
